odoo/addons/hr_holidays_summary_email/README.rst
odoo/addons/hr_holidays_summary_email/__init__.py
odoo/addons/hr_holidays_summary_email/__manifest__.py
odoo/addons/hr_holidays_summary_email/data/ir_cron.xml
odoo/addons/hr_holidays_summary_email/data/mail_template_data.xml
odoo/addons/hr_holidays_summary_email/i18n/hr_holidays_summary_email.pot
odoo/addons/hr_holidays_summary_email/i18n/it.po
odoo/addons/hr_holidays_summary_email/models/__init__.py
odoo/addons/hr_holidays_summary_email/models/hr_employee.py
odoo/addons/hr_holidays_summary_email/models/hr_leave.py
odoo/addons/hr_holidays_summary_email/models/res_company.py
odoo/addons/hr_holidays_summary_email/models/res_config_settings.py
odoo/addons/hr_holidays_summary_email/models/res_users.py
odoo/addons/hr_holidays_summary_email/readme/CONTRIBUTORS.rst
odoo/addons/hr_holidays_summary_email/readme/DESCRIPTION.rst
odoo/addons/hr_holidays_summary_email/readme/USAGE.rst
odoo/addons/hr_holidays_summary_email/static/description/icon.png
odoo/addons/hr_holidays_summary_email/static/description/index.html
odoo/addons/hr_holidays_summary_email/tests/__init__.py
odoo/addons/hr_holidays_summary_email/tests/test_hr_leave_summary_email.py
odoo/addons/hr_holidays_summary_email/views/hr_employee_views.xml
odoo/addons/hr_holidays_summary_email/views/res_config_settings.xml
odoo/addons/hr_holidays_summary_email/views/res_users_views.xml
odoo_addon_hr_holidays_summary_email-16.0.1.0.1.2.dist-info/METADATA
odoo_addon_hr_holidays_summary_email-16.0.1.0.1.2.dist-info/WHEEL
odoo_addon_hr_holidays_summary_email-16.0.1.0.1.2.dist-info/top_level.txt
odoo_addon_hr_holidays_summary_email-16.0.1.0.1.2.dist-info/RECORD
