Metadata-Version: 2.1
Name: odoo-addon-hr_holidays_summary_email
Version: 16.0.1.0.1.2
Summary: Notify employees with daily or weekly leaves summaries of their company.
Home-page: https://github.com/OCA/hr-holidays
Author: ForgeFlow, Odoo Community Association (OCA)
Author-email: support@odoo-community.org
License: AGPL-3
Classifier: Programming Language :: Python
Classifier: Framework :: Odoo
Classifier: Framework :: Odoo :: 16.0
Classifier: License :: OSI Approved :: GNU Affero General Public License v3
Requires-Python: >=3.10
Requires-Dist: odoo-addon-hr-holidays-settings<16.1dev,>=16.0dev
Requires-Dist: odoo<16.1dev,>=16.0a
